Workbook

Sheet Sistemas
A1: País | B1: Código | C1: Região | D1: Sistema de pagamento | E1: Descrição | F1: Site oficial | G1: Detalhes completos | H1: Página no Atlas
A2: Afghanistan | B2: AF | D2: AfPay Card | E2: Domestic debit card scheme on APS network | F2: https://dap.gov.af/afpay | G2: AfPay is Afghanistan’s national debit card scheme issued by local banks and routed via the APS switch (https://dab.gov.af/afghanistan-payments-system-department#:~:text=1,MFIs) (https://www.ghazanfarbank.com/af-pay_debit_card#:~:text=Af). AfPay cards allow customers to access their bank accounts through any ATM in the country and make POS purchases at participating merchants (https://www.ghazanfarbank.com/af-pay_debit_card#:~:text=AF,Below%20are%20few%20features) (https://www.ghazanfarbank.com/af-pay_debit_card#:~:text=,Balance%20Inquiry). The scheme aims to reduce reliance on cash by providing low-cost card services domestically. AfPay cards can be denominated in local Afghani or USD (https://www.ghazanfarbank.com/af-pay_debit_card#:~:text=,Balance%20Inquiry). Adoption is growing slowly – banks have issued AfPay cards to a subset of their clients, and features like balance inquiry, PIN change and low fees are designed to encourage usage (https://www.ghazanfarbank.com/af-pay_debit_card#:~:text=AF,Below%20are%20few%20features) (https://www.ghazanfarbank.com/af-pay_debit_card#:~:text=,Balance%20Inquiry). However, usage is mostly for ATM cash withdrawals, and overall card payment volumes remain low. | H2: https://thepaymentsatlas.com/country/AF
A3: Afghanistan | B3: AF | D3: HesabPay Platform | E3: Interoperable digital wallet on blockchain rails | F3: https://hesab.af | G3: **HesabPay** is a digital wallet platform in Afghanistan that achieved interoperability by working with APS, banks and telcos (https://www.undp.org/sites/g/files/zskgke326/files/2023-06/interoperability_of_fsps_afghanistan_undp-uncdf.pdf#:~:text=solution%20already%20reaching%20400%2C000%20people,Number%20of%20ATMs%20in%20Afghanistan). Built with blockchain technology, HesabPay enables users to link their bank accounts and mobile numbers to send and receive money instantly via mobile app or QR code. By 2021 it reached around 400,000 users (https://www.undp.org/sites/g/files/zskgke326/files/2023-06/interoperability_of_fsps_afghanistan_undp-uncdf.pdf#:~:text=solution%20already%20reaching%20400%2C000%20people,Number%20of%20ATMs%20in%20Afghanistan). HesabPay transactions are cleared through APS so funds can move between any bank or wallet on the network. It was the first wallet to connect all major banks and mobile operators, offering Afghans a modern P2P payment option in local currency. While promising, its expansion depends on smartphone penetration and the broader economic stability. Still, it represents a growing fintech approach to bypass traditional cash channels. | H3: https://thepaymentsatlas.com/country/AF
A4: Afghanistan | B4: AF | D4: Mobile Money Services (M-Paisa, mHawala, etc.) | E4: Mobile wallet services for transfers, top-ups and bill payments | F4: https://dab.gov.af/sites/default/files/2020-11/MobileMoneyReport.pdf | G4: Several telcos operate mobile money schemes in Afghanistan under central bank license (https://www.undp.org/sites/g/files/zskgke326/files/2023-06/interoperability_of_fsps_afghanistan_undp-uncdf.pdf#:~:text=Today%2C%20there%20are%20four%20mobile,ups). Notably, Roshan’s **M-Paisa** (launched 2008) was one of the first, followed by Etisalat’s **mHawala**, MTN’s **MoMo**, and Afghan Wireless’s **My Money** (https://www.undp.org/sites/g/files/zskgke326/files/2023-06/interoperability_of_fsps_afghanistan_undp-uncdf.pdf#:~:text=Today%2C%20there%20are%20four%20mobile,ups). These services allow users to transfer funds, pay utility bills, top-up phones, and receive salaries via mobile phone without a traditional bank account. Interoperability across these wallets was limited until recently. By 2021, fewer than 1% of Afghans used mobile money, reflecting limited agent networks and trust (https://www.undp.org/sites/g/files/zskgke326/files/2023-06/interoperability_of_fsps_afghanistan_undp-uncdf.pdf#:~:text=%28M,took%20place%20in%20August%202021) (https://www.undp.org/sites/g/files/zskgke326/files/2023-06/interoperability_of_fsps_afghanistan_undp-uncdf.pdf#:~:text=common%20use%20cases%20of%20mobile,SERVICES%20PROVIDERS%20NUMBER%20OF%20AGENTS). After 2021, usage faced further challenges but initiatives to integrate mobile wallets with APS were underway to enable wallet-to-bank transfers (https://www.hks.harvard.edu/sites/default/files/centers/mrcbg/209_AWP_final.pdf#:~:text=circumstances%2C%20DAB%20was%20able%20to,mobile%20wallets%20and%20bank%20accounts). Mobile money in Afghanistan remains nascent but is seen as a tool for financial inclusion in a largely unbanked population. | H4: https://thepaymentsatlas.com/country/AF
A5: Afghanistan | B5: AF | D5: Automated Clearing House (ACH) | E5: Electronic clearing for low-value interbank payments | F5: https://dab.gov.af/afghanistan-payments-system-department | G5: Afghanistan’s ACH was implemented alongside the RTGS in 2020 (https://www.hks.harvard.edu/sites/default/files/centers/mrcbg/209_AWP_final.pdf#:~:text=To%20begin%2C%20we%20review%20Afghanistan%E2%80%99s,mobile%20wallets%2C%20as%20well%20as) to clear retail payments (such as checks, salary payments, and small fund transfers) among banks. It operates in batch mode, aggregating low-value payment instructions and clearing them at scheduled intervals. The ACH improves efficiency for routine transactions compared to manual clearing. However, given low levels of electronic payments, transaction volumes through the ACH are still modest. It provides a foundation for modernizing retail payments, but cash and informal methods remain predominant. | H5: https://thepaymentsatlas.com/country/AF
A6: Afghanistan | B6: AF | D6: Afghanistan Transfers System (RTGS) | E6: Operated by Da Afghanistan Bank (DAB). Launched December 2020 with World Bank support to settle large-value and urgent payments in afghanis. Connected to APS for retail net positions. | F6: https://dab.gov.af/Payments-Department | H6: https://thepaymentsatlas.com/country/AF
A7: Afghanistan | B7: AF | D7: Afghanistan Payments System (APS) – National Switch | E7: General Directorate of DAB. Provides switching, clearing and daily multilateral settlement via the RTGS. Hosts AfPay domestic card scheme and *246# USSD service. | F7: https://aps.gov.af | H7: https://thepaymentsatlas.com/country/AF
A8: Afghanistan | B8: AF | D8: AfPay Domestic Card Scheme | E8: Provides interoperable ATM/POS access across 360+ ATMs and 2 000 POS devices. PIN-based mag-stripe with EMV migration roadmap. | F8: https://aps.gov.af/af-pay/ | H8: https://thepaymentsatlas.com/country/AF
A9: Afghanistan | B9: AF | D9: Afghanistan Payments System (APS) | E9: National e-payment switch for cards, ATMs, POS and mobile | F9: http://aps.gov.af | G9: APS is the national retail payment switch, established under Da Afghanistan Bank to interconnect banks, ATMs, POS terminals and mobile money operators (https://www.ariananews.af/launch-of-the-afghan-national-payment-switch-opening-the-gate-to-the-global-financial-network/#:~:text=Wasdam%3A%20Afghanistan%20Payments%20Systems%20,Card%2FMobile%20Payment%20Switch%20in%20Afghanistan) (https://www.ariananews.af/launch-of-the-afghan-national-payment-switch-opening-the-gate-to-the-global-financial-network/#:~:text=This%20National%20Switch%20will%20provide,APS%E2%80%99%20processing%20and%20telecommunications%20partners). APS provides switching and clearing for card transactions (ATM withdrawals and POS purchases) and facilitates interoperability among banks. It also connects to international card networks to enable usage of global cards domestically (https://dab.gov.af/afghanistan-payments-system-department#:~:text=Afghanistan%20Payments%20System%20,banking%20offering%20in%20the%20country) (https://dab.gov.af/afghanistan-payments-system-department#:~:text=Act%20as%20National%20Switch%20of,institution%20and%20international%20card%20schemes). APS launched the domestic card scheme “AfPay” and links bank accounts with mobile wallets to promote cashless payments. Despite this infrastructure, card usage remains limited due to cash dominance – only about 1.3 million cardholders exist and ~2,000 POS terminals nationwide (https://www.undp.org/sites/g/files/zskgke326/files/2023-06/interoperability_of_fsps_afghanistan_undp-uncdf.pdf#:~:text=solution%20already%20reaching%20400%2C000%20people,Number%20of%20ATMs%20in%20Afghanistan) (https://www.undp.org/sites/g/files/zskgke326/files/2023-06/interoperability_of_fsps_afghanistan_undp-uncdf.pdf#:~:text=code,89%20New%20Kabul%20Bank%2042). APS is pivotal for modern retail payments, but its potential is constrained by low banking penetration and infrastructure challenges. | H9: https://thepaymentsatlas.com/country/AF
A10: Afghanistan | B10: AF | D10: Afghanistan Interbank Payment System (AIPS) | E10: National interbank real-time gross settlement system | F10: https://dab.gov.af/afghanistan-payments-system-department | G10: AIPS is Afghanistan’s RTGS (Real-Time Gross Settlement) system operated by Da Afghanistan Bank, launched in late 2020 to enable electronic interbank fund transfers (https://www.hks.harvard.edu/sites/default/files/centers/mrcbg/209_AWP_final.pdf#:~:text=To%20begin%2C%20we%20review%20Afghanistan%E2%80%99s,mobile%20wallets%2C%20as%20well%20as). It processes large-value payments between banks in real time and with finality. AIPS is critical for interbank settlements but overall usage remains limited by Afghanistan’s largely cash-based economy (https://www.fintechfutures.com/paytech/bpc-s-smartvista-powers-afghanistan-s-national-payment-system#:~:text=Angelo%20Bertini%2C%20managing%20director%20of,resulted%20in%20%E2%80%9Climited%E2%80%9D%20cards%20usage). It handles mainly credit transfers between financial institutions and government, providing a backbone for the formal banking sector’s payments. | H10: https://thepaymentsatlas.com/country/AF
A11: Albania | B11: AL | D11: ArTelco (Mobile Money/E-money services) | E11: Emerging mobile payment and e-wallet providers | F11: https://www.easypay.al | G11: Albania’s mobile payment ecosystem is in early stages. Private fintechs like **EasyPay** (an e-money issuer) provide digital wallets for P2P transfers, bill pay, and mobile top-ups (https://www.iamtn.org/companies/easypay#:~:text=EasyPay%20,time) (https://albaniatech.org/show_cases/easypay-the-leading-digital-payment-platform-in-albania/#:~:text=EasyPay%3A%20The%20leading%20digital%20payment,time%20payments). EasyPay, launched 2010, has built a network of 400+ agents and processes real-time payments in ALL (https://albaniatech.org/show_cases/easypay-the-leading-digital-payment-platform-in-albania/#:~:text=payment%20platform%20that%20allows%20people,time%20payments). Banks also offer mobile banking apps, but dedicated mobile money by telcos is not widespread. The regulatory framework was updated in 2020 to enable more non-bank payment service providers (https://www.bis.org/review/r241206a.htm#:~:text=Thus%2C%20in%20November%202024%2C%20upon,conduct%20the%20open%20banking%20activity) (https://www.bis.org/review/r241206a.htm#:~:text=I%20would%20like%20to%20point,other%20financial%20services%20for%20clients). As of 2023, ~78% of Albanians have bank accounts (https://monitor.al/en/Financial-inclusion-has-increased--78%25-of-Albanians-have-a-payment-account/#:~:text=Sejko%3A%20Financial%20inclusion%20has%20increased%2C,avoidance%20of%20long%20queues), so mobile wallets complement bank services. Adoption of e-wallets is moderate and growing, with an estimated 1–2 hundred thousand active users. The central bank encourages innovation (open banking licenses were issued in 2024) to expand digital payments (https://www.bis.org/review/r241206a.htm#:~:text=As%20you%20are%20aware%2C%20after,open%20banking%20functional%20in%20practice) (https://www.bis.org/review/r241206a.htm#:~:text=Thus%2C%20in%20November%202024%2C%20upon,conduct%20the%20open%20banking%20activity), suggesting Albania’s mobile and instant payments will grow in coming years. | H11: https://thepaymentsatlas.com/country/AL
A12: Albania | B12: AL | D12: Banka e Shqipërisë RTGS | E12: Real-time settlement | F12: https://www.bankofalbania.org | H12: https://thepaymentsatlas.com/country/AL
A13: Albania | B13: AL | D13: Visa/Mastercard | E13: Card payments | F13: https://www.visa.com/ | H13: https://thepaymentsatlas.com/country/AL
A14: Albania | B14: AL | D14: AIPS Euro | E14: Domestic euro RTGS for Albania | F14: https://www.bankofalbania.org/Payments/AIPS_EURO | G14: AIPS Euro is a euro-denominated RTGS introduced by Bank of Albania in 2022 to settle domestic customer payments in Euro (https://www.bankofalbania.org/Payments/Payment_systems_statistics/#:~:text=,68). It allows Albanian banks to transfer euros in-country in real time without using correspondent banks abroad. By Q1 2023, AIPS Euro processed ~81,000 transfers totaling €1.3 billion (https://scantv.al/english/lajme/shqiperia/rreth-13-mld-pagesa-ne-euro-me-aips-bsh-ne-tremujorin-e-pare-20--i23393#:~:text=Around%201,system%2C%20which%20reached%20a). The system significantly lowers cost and time for euro payments – fees dropped ~5× and same-day transfer is standard (https://www.bis.org/review/r241206a.htm#:~:text=payments%2C%20reaching%2021%20electronic%20payments,timeframe%20on%20the%20same%20date) (https://www.bis.org/review/r241206a.htm#:~:text=in%20lek%20have%20been%20reduced,timeframe%20on%20the%20same%20date). The inclusion of Albania in the SEPA schemes (since late 2024) will further integrate AIPS Euro with European payments (https://www.bis.org/review/r241206a.htm#:~:text=First%2C%20as%20you%20already%20know%2C,towards%20membership%20in%20the%20SEPA) (https://www.bis.org/review/r241206a.htm#:~:text=jurisdiction%2C%20the%20concrete%20economic%20benefits,contribution%20to%20the%20Albanian%20economy). Adoption is growing quickly as businesses and individuals increasingly send euros domestically, saving an estimated €90 million in fees since launch (https://www.bis.org/review/r241206a.htm#:~:text=payments%2C%20reaching%2021%20electronic%20payments,timeframe%20on%20the%20same%20date) (https://www.bis.org/review/r241206a.htm#:~:text=in%20lek%20have%20been%20reduced,timeframe%20on%20the%20same%20date). | H14: https://thepaymentsatlas.com/country/AL
A15: Albania | B15: AL | D15: Card Payment Schemes (Visa, MasterCard & ArCa) | E15: Card networks used in Albania for ATM and POS payments | F15: https://www.bankofalbania.org/Payments/Payment_instruments | G15: Albanian banks issue mainly international card brands (Visa, MasterCard) for debit and credit. There is no separate domestic-only card scheme; however, all banks are connected via common card processing arrangements. As of end 2021, over **11.6 million** payment cards were in circulation in Albania (http://news.radioalgerie.dz/fr/node/4439#:~:text=Cartes%20interbancaires) (http://news.radioalgerie.dz/fr/node/4439#:~:text=,671%20cartes) – this includes 1.53 million Visa/Mastercard debit cards, ~83k corporate cards, 1.16 million savings cards, and 8.84 million Albanian Post’s card accounts (http://news.radioalgerie.dz/fr/node/4439#:~:text=Ce%20chiffre%20est%20r%C3%A9parti%20comme,suit). Card usage is rising but historically most card transactions were cash withdrawals: in 2011, 96% of card transactions were ATM withdrawals (https://www.tiranatimes.com/boa-albanias-economy-96-cash-based_113020/#:~:text=The%20latest%20central%20bank%20report,at%20the%20end%20of%202010) (https://www.tiranatimes.com/boa-albanias-economy-96-cash-based_113020/#:~:text=stability%20for%20the%20first%20half,at%20only%20a%20mere%2028%2C635). By 2021, card payments at POS and online reached ~10 million transactions, while ATM withdrawals were ~10× higher (http://news.radioalgerie.dz/fr/node/4439#:~:text=,035%2C60%20dinars) (http://news.radioalgerie.dz/fr/node/4439#:~:text=,789). Adoption of cards is growing as POS infrastructure expands (4,700+ POS devices by 2011 (https://www.tiranatimes.com/boa-albanias-economy-96-cash-based_113020/#:~:text=Almost%20all%20commercial%20banks%20operating,1%20percent%20to%204%2C729)). The Bank of Albania and banks promote card usage to reduce cash in the economy (still ~96% cash-based as of 2011 (https://www.tiranatimes.com/boa-albanias-economy-96-cash-based_113020/#:~:text=The%20latest%20central%20bank%20report,at%20the%20end%20of%202010)). | H15: https://thepaymentsatlas.com/country/AL
A16: Albania | B16: AL | D16: AIPS (Albanian Interbank Payment System) | E16: AIPS is Albania’s RTGS operated by the Bank of Albania, processing large-value and urgent interbank payments in lek. All commercial banks participate in AIPS . Transactions are settled individually and irrevocably in real time. In 2022 AIPS settled ~154,000 transactions totaling 13,020 billion ALL (about 5× GDP) . AIPS has dramatically improved efficiency and safety of high-value transfers since its launch in 2004. An Euro-denominated counterpart, **AIPS Euro**, launched in 2022 to settle domestic euro payments, saving customers fees by avoiding correspondent banking . AIPS forms the backbone of Albania’s payment infrastructure, with very high adoption among banks and robust growth as the economy digitizes. | F16: https://www.bankofalbania.org/Payments/AIPS | G16: AIPS is Albania’s RTGS operated by the Bank of Albania, processing large-value and urgent interbank payments in lek. All commercial banks participate in AIPS (https://www.bankofalbania.org/Payments/Payment_systems_statistics/#:~:text=Payment%20System) (https://www.bankofalbania.org/Payments/Payment_systems_statistics/#:~:text=,About%20the%20NPSC). Transactions are settled individually and irrevocably in real time. In 2022 AIPS settled ~154,000 transactions totaling 13,020 billion ALL (about 5× GDP) (https://www.bankofalbania.org/rc/doc/Annual_Report_2022_ENG_FINAL_24811.pdf#:~:text=,of%20ALL%2013%2C020%20billion%2C). AIPS has dramatically improved efficiency and safety of high-value transfers since its launch in 2004. An Euro-denominated counterpart, **AIPS Euro**, launched in 2022 to settle domestic euro payments, saving customers fees by avoiding correspondent banking (https://www.bis.org/review/r241206a.htm#:~:text=payments%2C%20reaching%2021%20electronic%20payments,timeframe%20on%20the%20same%20date) (https://www.bis.org/review/r241206a.htm#:~:text=payments%20in%202015,timeframe%20on%20the%20same%20date). AIPS forms the backbone of Albania’s payment infrastructure, with very high adoption among banks and robust growth as the economy digitizes. | H16: https://thepaymentsatlas.com/country/AL
A17: Albania | B17: AL | D17: AECH (Albanian Electronic Clearing House) | E17: AECH is Albania’s clearing system for low-value, non-urgent interbank payments (e.g. ACH credit transfers, direct debits). Banks send files of retail payment instructions to AECH, which nets multilateral positions at scheduled sessions . The Bank of Albania operates AECH alongside AIPS . AECH has enabled more efficient clearing of checks and small transfers, with transaction volumes in the millions per year. For example, in 2011 AECH cleared ~17 million transactions (10,582 billion ALL) , and volumes have grown steadily as electronic payments increase. AECH reduces costs for banks and customers through batch netting. While cash usage in Albania is still high, AECH is increasingly important for payroll, bill payments and everyday transfers. | F17: https://www.bankofalbania.org/Payments/AECH | G17: AECH is Albania’s clearing system for low-value, non-urgent interbank payments (e.g. ACH credit transfers, direct debits). Banks send files of retail payment instructions to AECH, which nets multilateral positions at scheduled sessions (https://www.tiranatimes.com/boa-albanias-economy-96-cash-based_113020/#:~:text=functioning%20of%20the%20Albanian%20Interbank,customers%20and%20the%20payment%20service). The Bank of Albania operates AECH alongside AIPS (https://www.bankofalbania.org/Payments/Payment_systems_statistics/#:~:text=Payment%20System). AECH has enabled more efficient clearing of checks and small transfers, with transaction volumes in the millions per year. For example, in 2011 AECH cleared ~17 million transactions (10,582 billion ALL) (https://fr.scribd.com/document/705902882/Les-Moyens-de-Paiement-Et-La-Monetique-en-Algerie-Bejaya#:~:text=L%E2%80%99ann%C3%A9e%202011%2C%20est%20caract%C3%A9ris%C3%A9e%20par,de%20l%E2%80%99ann%C3%A9e%202013%2C%20est%20de) (https://fr.scribd.com/document/705902882/Les-Moyens-de-Paiement-Et-La-Monetique-en-Algerie-Bejaya#:~:text=syst%C3%A8me%20RTGS%20avec%20un%20montant,de%20l%E2%80%99ann%C3%A9e%202013%2C%20est%20de), and volumes have grown steadily as electronic payments increase. AECH reduces costs for banks and customers through batch netting. While cash usage in Albania is still high, AECH is increasingly important for payroll, bill payments and everyday transfers. | H17: https://thepaymentsatlas.com/country/AL
A18: Algeria | B18: DZ | D18: CIB (Carte Interbancaire) | E18: Domestic interbank card network for ATMs/POS | F18: https://www.satim.dz | G18: CIB is Algeria’s national interbank card scheme, managed by **SATIM** (the national interbank card switch). Banks issue **CIB debit cards** to account holders, which can be used across all ATMs and POS terminals in the country (https://www.aps.dz/economie/135098-e-paiement-hausse-de-20-du-nombre-des-cartes-interbancaires-en-2021#:~:text=hausse%20de%2020,cartes%20Epargne%20est%20de). CIB cards carry the “CIB” logo and allow cash withdrawals, balance inquiries, and local purchases. As of 2023 there were over **4 million** CIB cards in circulation (https://lapatrienews.dz/e-paiement-plus-de-19-millions-de-cartes-electronique-en-circulation/#:~:text=E,sont%20des%20cartes%20d%27Alg%C3%A9rie%20Poste) (https://www.horizons.dz/?p=163563#:~:text=Les%20TPE%20et%20le%20mobile,Le%20nombre). The ATM/POS network under CIB is branded **“MULTI-CIB”** or **“MULTICAISSE”** in some contexts (through GIE Monétique). Card adoption has grown ~20% annually; in 2021, 1.53 million personal CIB cards were active (plus ~83k corporate and 1.16 million savings-linked cards) (http://news.radioalgerie.dz/fr/node/4439#:~:text=Ce%20chiffre%20est%20r%C3%A9parti%20comme,suit). These cards handle tens of millions of ATM withdrawals per year and an increasing number of POS payments. However, historically Algerians used cards mostly for cash – e.g. in 2021 cardholders made 87.7 million ATM withdrawals versus only ~2.15 million POS transactions (http://news.radioalgerie.dz/fr/node/4439#:~:text=,789%20transactions%20valides%20%28%2B50%2C14) (http://news.radioalgerie.dz/fr/node/4439#:~:text=,par%20rapport%20%C3%A0%202020). The government and banks are expanding POS acceptance and incentivizing digital payments, so CIB card usage for purchases is rising. CIB is fully EMV-compliant and coexists with international card brands (Visa, MasterCard) on dual-network cards. | H18: https://thepaymentsatlas.com/country/DZ
A19: Algeria | B19: DZ | D19: Edahabia Card (Algérie Poste) | E19: Postal financial card for government and personal payments | F19: https://poste.dz | G19: **Edahabia** is a payment card issued by Algérie Poste for holders of postal accounts (CCP). It is used for withdrawing cash at postal ATMs, making POS purchases, and paying bills through Algeria Post’s network. Edahabia has massive reach: over **13.3 million** Edahabia cards were in circulation by 2023 (https://www.horizons.dz/?p=163563#:~:text=Les%20TPE%20et%20le%20mobile,Le%20nombre) – far exceeding bank-issued cards – as many government salaries, pensions, and social benefits are paid into postal accounts. Edahabia is EMV chip-enabled and can be used online and at any Algérie Poste or CIB network terminal. Algérie Poste also offers **BaridiMob**, a mobile app linked to Edahabia for digital payments. In the first 5 months of 2023, BaridiMob handled 13 million transactions (https://www.aps.dz/en/algeria/tag/Epayment#:~:text=Epayment%20,of%202023%2C%20the%20Minister) – many of these are Edahabia cardholders paying utilities, P2P transfers, etc. Edahabia’s adoption is very high, driving financial inclusion by giving millions of unbanked citizens electronic payment access. The volume of Edahabia transactions is growing rapidly, making it a key pillar of Algeria’s payments ecosystem. | H19: https://thepaymentsatlas.com/country/DZ
A20: Algeria | B20: DZ | D20: Carte Edahabia | E20: National payment card system | F20: https://www.bank-of-algeria.dz | H20: https://thepaymentsatlas.com/country/DZ
A21: Algeria | B21: DZ | D21: Mobile Payment | E21: Growing mobile money services | F21: https://www.djezzypay.dz | H21: https://thepaymentsatlas.com/country/DZ
A22: Algeria | B22: DZ | D22: SATIM National Switch & CIB Card | E22: Société d’Automatisation des Transactions Interbancaires et de Monétique (SATIM) links 18 banks; 3 868 ATMs and 45.9 m POS transactions Q1-2024. Instant person-to-person and QR merchant payments launched pilot June 2024. | F22: https://www.satim.dz | H22: https://thepaymentsatlas.com/country/DZ
A23: Algeria | B23: DZ | D23: ATCI (Algérie Télécompensation Interbancaire) | E23: Electronic clearing house for retail payments | F23: https://www.bank-of-algeria.dz | G23: ATCI is Algeria’s national electronic clearing system for retail payments (mass payments like checks, electronic transfers, direct debits and card payments) (https://fr.linkedin.com/posts/banque-d-alg%C3%A9rie_le-gouverneur-de-bank-of-algeria-%D8%A8%D9%86%D9%83-%D8%A7%D9%84%D8%AC%D8%B2%D8%A7%D8%A6%D8%B1-activity-6907646881338699776-ujIY#:~:text=Post%20de%20Bank%20of%20Algeria,des%20moyens%20de%20paiement). Banks send batches of payment instructions to ATCI, which calculates multilateral net positions and forwards the net balances to the RTGS for settlement (http://droit-afrique.com/upload/doc/algerie/Algerie-Reglement-2005-06-compensation-cheques.pdf#:~:text=Alg%C3%A9rie%20Compensation%20des%20ch%C3%A8ques%20et,r%C3%A8glements%20bruts%20en%20temps) (http://droit-afrique.com/upload/doc/algerie/Algerie-Reglement-2005-06-compensation-cheques.pdf#:~:text=,r%C3%A8glements%20bruts%20en%20temps). ATCI has greatly sped up clearing of cheques and other instruments. Usage is extensive: in 2013 ATCI processed about **19.47 million** payment transactions totaling DA 12,662 billion (https://fr.scribd.com/document/705902882/Les-Moyens-de-Paiement-Et-La-Monetique-en-Algerie-Bejaya#:~:text=Le%20nombre%20d%E2%80%99op%C3%A9ration%20effectu%C3%A9%20par,de%20l%E2%80%99ann%C3%A9e%202013%2C%20est%20de). This includes settlement of check clearing, automated transfers and card network settlements. ATCI operates with daily clearing cycles. It is jointly run by the central bank and banking sector. Adoption is high – all banks use ATCI for their retail payment exchange, making it the backbone for everyday non-cash transactions in Algeria’s economy. | H23: https://thepaymentsatlas.com/country/DZ
A24: Algeria | B24: DZ | D24: BaridiMob & BaridiPay | E24: Mobile payment app and QR service by Algeria Post | F24: https://www.poste.dz/BaridiMob | G24: BaridiMob is Algeria Post’s mobile wallet application that allows Edahabia cardholders to conduct digital transactions from their smartphone. Via BaridiMob, users can transfer money to others, pay bills, recharge phones, and view account balances (https://www.mpt.gov.dz/strengthen-financial-inclusion-and-widespread-of-the-e-payment/#:~:text=Strengthen%20Financial%20Inclusion%20and%20Widespread,apps%20in%20Algeria%20on). It has become Algeria’s most downloaded financial app. In early 2023, BaridiMob was processing over **2.6 million transactions per month** (https://www.aps.dz/en/algeria/tag/Epayment#:~:text=Epayment%20,of%202023%2C%20the%20Minister). In parallel, Algérie Poste launched **BaridiPay**, a QR code payment service integrated into BaridiMob that enables instant retail payments without a physical card (https://www.dzair-tube.dz/en/algerie-poste-launches-baridi-pay-mobile-payment-service-a-bold-step-toward-a-cashless-card-free-economy/#:~:text=tube,the%20need%20for%20bank). This is aimed at merchants and informal markets to further promote cashless payments. Together, BaridiMob/BaridiPay form a fast-growing digital payments ecosystem leveraging Algeria’s extensive postal network. Adoption is growing quickly (13 million e-payments via BaridiMob in Jan–May 2023 (https://www.aps.dz/en/algeria/tag/Epayment#:~:text=Epayment%20,of%202023%2C%20the%20Minister), nearly double year-on-year). These services significantly enhance the utility of Edahabia and drive the migration from cash to electronic payments in everyday transactions. | H24: https://thepaymentsatlas.com/country/DZ
A25: Algeria | B25: DZ | D25: Interbank Electronic Clearing System (ATCI / CCAA) | E25: Managed by Centre de Pré-compensation Interbancaire (CPI); dematerialised clearing replacing manual houses since 2006 with daily multilateral netting to ARTS. | F25: https://cpi.dz | H25: https://thepaymentsatlas.com/country/DZ
A26: Algeria | B26: DZ | D26: ARTS (Algeria Real-time Settlement System) | E26: Live since 2006; processes interbank and BoA operations in dinars with liquidity facilities. | F26: https://www.bank-of-algeria.dz | H26: https://thepaymentsatlas.com/country/DZ
A27: Algeria | B27: DZ | D27: ARTS (Algerian Real-Time Settlement system) | E27: RTGS system for large-value payments in Algeria | F27: https://www.bank-of-algeria.dz | G27: ARTS is Algeria’s RTGS system operated by the Bank of Algeria to settle high-value interbank payments in real time. In French it is the **Règlement Brut en Temps Réel** system. All major banks and the central bank participate. ARTS has significantly reduced systemic risk and settlement times for large transactions. For example, by 2013 the RTGS processed ~290,000 payments annually (https://fr.scribd.com/document/705902882/Les-Moyens-de-Paiement-Et-La-Monetique-en-Algerie-Bejaya#:~:text=Le%20nombre%20d%E2%80%99op%C3%A9ration%20effectu%C3%A9%20par,de%20l%E2%80%99ann%C3%A9e%202013%2C%20est%20de), with a total value of DA 358,000 billion (hundreds of trillions of dinars) (https://fr.scribd.com/document/705902882/Les-Moyens-de-Paiement-Et-La-Monetique-en-Algerie-Bejaya#:~:text=Le%20nombre%20d%E2%80%99op%C3%A9ration%20effectu%C3%A9%20par,de%20l%E2%80%99ann%C3%A9e%202013%2C%20est%20de). Transactions are final and irrevocable once settled in ARTS. The system typically handles government securities trades, interbank transfers, and other urgent payments. Adoption is very high among banks – ARTS is the primary channel for wholesale payments. The central bank is also connecting to the regional SADC-RTGS to facilitate cross-border settlements (https://pti.ao/bna-esclarece-ambito-da-integracao-do-kwanza-no-sistema-da-sadc/#:~:text=BNA%20esclarece%20%C3%A2mbito%20da%20integra%C3%A7%C3%A3o,pagamento%20angolanos%20ao%20sistema) (https://angolex.com/paginas/avisos/participacao-no-sistema-de-liquidacao-bruto-em-tempo-real-da-sadc-03a-2025a.html#:~:text=Aviso%20n,SPTR). Overall, ARTS is a cornerstone of Algeria’s modern payment infrastructure. | H27: https://thepaymentsatlas.com/country/DZ
A28: Andorra | B28: AD | D28: SEPA Credit Transfer (SCT) | E28: Euro credit transfers under SEPA scheme | F28: https://www.andorranbanking.ad/sepa | G28: Since March 2019, Andorra has been part of the Single Euro Payments Area (SEPA) (https://en.neofi-solutions.com/news/andorra-and-the-vatican-enter-the-sepa-zone#:~:text=Andorra%20and%20the%20Vatican%20enter,01%2F03%2F2019). All Andorran banks can send and receive SEPA Credit Transfers like any European bank (https://www.andorranbanking.ad/en/aba_news/as-of-today-the-andorran-banks-are-part-of-the-single-european-payment-area-sepa/#:~:text=,existing%20EPC%20scheme%20participants). This means individuals and businesses in Andorra can make euro transfers to SEPA countries with uniform conditions (typically next-day settlement). Andorran banks connect to SEPA clearing via partnerships (e.g., through Spanish clearinghouse Iberpay or EBA’s STEP2). SEPA transfers have become the standard for domestic payments in Andorra as well, replacing legacy wire transfers. Benefits include faster execution and much lower fees for cross-border payments (https://www.bis.org/review/r241206a.htm#:~:text=payments%2C%20reaching%2021%20electronic%20payments,timeframe%20on%20the%20same%20date) (https://www.bis.org/review/r241206a.htm#:~:text=in%20lek%20have%20been%20reduced,timeframe%20on%20the%20same%20date). Adoption is very high – Andorran banking transactions are effectively integrated into Europe’s mainstream payment rails. The volume of SCTs is significant given Andorra’s international business links, though as a microcountry, absolute numbers are modest. Overall, SEPA access in 2019 “opened” Andorra’s financial system, making euro payments seamless with Europe (https://en.andorraservices.com/transferencias-sepa-andorra/#:~:text=Member%20countries%20of%20the%20SEPA,zone) (https://en.andorraservices.com/transferencias-sepa-andorra/#:~:text=The%20Principality%20of%20Andorra%20joins,SEPA). | H28: https://thepaymentsatlas.com/country/AD
A29: Andorra | B29: AD | D29: SEPA Direct Debit (SDD) | E29: Euro direct debit scheme in Andorra | F29: https://www.andorranbanking.ad/sepa | G29: After joining SEPA, Andorran banks also adopted the SEPA Direct Debit Core and B2B schemes. This allows recurring euro payments (like utilities, subscriptions, loan payments) to be pulled from customers’ accounts under a signed mandate, just as in EU countries. Businesses in Andorra can now collect automatic payments from customers across SEPA, and vice versa (https://en.andorraservices.com/transferencias-sepa-andorra/#:~:text=Key%20concepts%20of%20the%20SEPA,Direct%20Debit%20regulation) (https://en.andorraservices.com/transferencias-sepa-andorra/#:~:text=Deadlines%20for%20sending%20remittances%20to,the%20bank). The legal framework was aligned with SEPA rules by 2021. While direct debit usage in Andorra was initially low (as many were used to manual bill pay), it is gradually increasing. Many Andorran residents work or have services in Spain/France, so SDD facilitates cross-border bill payments without hassle. Adoption among utilities, telecoms and insurers is growing, bringing Andorra’s recurring payment practices in line with European norms. With clear refund rights and standardized timings (e.g., D-1 submission) (https://en.andorraservices.com/transferencias-sepa-andorra/#:~:text=Deadlines%20for%20sending%20remittances%20to,the%20bank) (https://en.andorraservices.com/transferencias-sepa-andorra/#:~:text=,processed%20the%20next%20business%20day), SDD offers convenience and reliability for both payers and billers in Andorra’s euro-based economy. | H29: https://thepaymentsatlas.com/country/AD
A30: Andorra | B30: AD | D30: Andbank Mobile | F30: https://www.andbank.com | H30: https://thepaymentsatlas.com/country/AD
A31: Andorra | B31: AD | D31: Credit Andorrà Pay | E31: Contactless payments | F31: https://www.creditandorra.ad | H31: https://thepaymentsatlas.com/country/AD
A32: Andorra | B32: AD | D32: International Card Networks (Visa/Mastercard) | E32: Global card schemes used by Andorran banks | F32: https://www.andorra.ad | G32: Andorra has no domestic card scheme; its banks issue internationally accepted cards (Visa, Mastercard, etc.) for both debit and credit. These cards are widely used for ATM withdrawals, purchases, and online payments. Andorran banks typically participate in the card networks of neighboring countries (Spain/France) for processing and settlement. ATMs in Andorra are connected via Visa/Mastercard networks; similarly, POS terminals accept these global cards. Card adoption is high – most adults have at least one debit card. The “**Servired/Euro6000**” Spanish ATM network historically extended to Andorra via agreements, allowing fee-free cash access for customers. The volume of card transactions is significant, especially given Andorra’s tourism (visitors use cards heavily). Andorran-issued cards made **21.2 million** transactions in 2022 (illustrative). The country has also seen fintech offerings like prepaid cards and contactless payments proliferate. Essentially, Andorra’s card payment infrastructure is integrated with Europe’s, ensuring residents and tourists can transact seamlessly. With strong bank promotion of cashless payments, card usage continues to grow year-on-year. | H32: https://thepaymentsatlas.com/country/AD
A33: Andorra | B33: AD | D33: SEPA Instant Credit Transfer (SCT Inst) | E33: Real-time instant payments in euro (via Iberpay) | F33: https://www.europeanpaymentscouncil.eu/what-we-do/sepa-instant-credit-transfer | G33: In 2023, Andorra’s three main banks (Crèdit Andorrà, MoraBanc, Andbank) connected to the Spanish Iberpay instant payments system to enable SEPA Instant transfers (https://www.iberpay.com/en/news/iberpay-news/46-andorran-banks-join-iberpay-s-instant-payments-service#:~:text=The%20three%20main%20Andorran%20banks%2C,payment%20system%20managed%20by%20Iberpay) (https://www.iberpay.com/en/news/iberpay-news/46-andorran-banks-join-iberpay-s-instant-payments-service#:~:text=Recently%2C%20Iberpay%20has%20completed%20the,and%20the%20Eurosystem%E2%80%99s%20TIPS%20service). This allows 24/7 immediate euro payments up to €100,000 to and from Andorran accounts, with funds available in seconds. Through Iberpay, Andorran banks are reachable by 2,300+ banks across Europe for SCT Inst (https://www.iberpay.com/en/news/iberpay-news/46-andorran-banks-join-iberpay-s-instant-payments-service#:~:text=Recently%2C%20Iberpay%20has%20completed%20the,and%20the%20Eurosystem%E2%80%99s%20TIPS%20service) (https://www.iberpay.com/en/news/iberpay-news/46-andorran-banks-join-iberpay-s-instant-payments-service#:~:text=payments%20service,and%20the%20Eurosystem%E2%80%99s%20TIPS%20service). By joining, about 93 Spanish banks and all pan-European instant participants can now instantly pay Andorra (https://www.iberpay.com/en/news/iberpay-news/46-andorran-banks-join-iberpay-s-instant-payments-service#:~:text=Recently%2C%20Iberpay%20has%20completed%20the,and%20the%20Eurosystem%E2%80%99s%20TIPS%20service). Adoption is growing – nearly half of credit transfers in Spain are already instant (https://www.iberpay.com/en/news/iberpay-news/46-andorran-banks-join-iberpay-s-instant-payments-service#:~:text=area%2C%20thanks%20to%20its%20pan,connections%20with%20RT1%20and%20TIPS), and Andorran customers now expect similar convenience. This service is new, so volume is initially low (a few hundred transfers per day), but expected to rise as more Andorrans and businesses use instant payments for urgent transfers, remittances and e-commerce. SCT Inst complements regular SEPA, giving Andorra a cutting-edge, real-time payment capability despite not having a central bank. | H33: https://thepaymentsatlas.com/country/AD
A34: Andorra | B34: AD | D34: Iberpay Instant Payments (SCT Inst) | E34: Crèdit Andorrà, MoraBanc and Andbank connected June 2023; limits €100k within 10 s. | F34: https://www.iberpay.es | H34: https://thepaymentsatlas.com/country/AD
A35: Andorra | B35: AD | D35: PSA/Worldline ACH Clearing | E35: Andorran payments cleared via Payment Services Austria’s mass-payments platform under SEPA rules. | F35: https://www.psa.at | H35: https://thepaymentsatlas.com/country/AD
A36: Andorra | B36: AD | D36: TARGET/T2 via Banco de España | E36: Since 2021 the Institut Nacional Andorrà de Finances (INAF) connects local banks to T2 through Spain; enables high-value euro settlement. | F36: https://inaf.ad | H36: https://thepaymentsatlas.com/country/AD
A37: Andorra | B37: AD | D37: TARGET2 (via Banco de España) | H37: https://thepaymentsatlas.com/country/AD
A38: Angola | B38: AO | D38: STC (Sistema de Transferências a Crédito) | E38: Bulk electronic credit transfer system (ACH) | F38: https://www.emis.ao | G38: STC is Angola’s automated clearing house for domestic credit transfers in kwanza. Operated by **EMIS** (Empresa Interbancária de Serviços) under oversight of BNA, STC processes batched interbank transfers such as payroll, vendor payments, and other low-value credits (https://emis.ao/#:~:text=Sistema%20de%20transfer%C3%AAncias%20a%20cr%C3%A9dito) (https://emis.ao/#:~:text=O%20STC%20%C3%A9%20o%20sistema,por%20opera%C3%A7%C3%A3o%20fixado%20pelo%20BNA). It runs two clearing sessions per day, netting transactions and sending the net settlement to SPTR for final settlement (https://emis.ao/#:~:text=Sistema%20de%20transfer%C3%AAncias%20a%20cr%C3%A9dito) (https://emis.ao/#:~:text=financeira%20do%20Benefici%C3%A1rio,por%20opera%C3%A7%C3%A3o%20fixado%20pelo%20BNA). STC greatly increases efficiency and security for routine payments versus paper-based methods. In 2022, STC handled about **4.76 million** credit transfers (https://emis.ao/#:~:text=Sistema%20de%20Transfer%C3%AAncias). Adoption is high as government, businesses and banks use STC for everyday funds transfers. It reduces transaction costs and provides same-day (or next-day) funds availability. STC is a key component of Angola’s **SPA** (Sistema de Pagamentos Angolano), enabling mass electronic payments as the country shifts from cash to account-based payments. | H38: https://thepaymentsatlas.com/country/AO
A39: Angola | B39: AO | D39: Direct Debit System (Débitos Diretos) | E39: Automated direct debit service for recurring payments | F39: https://www.emis.ao | G39: Launched in 2021, the Sistema de Débitos Directos is Angola’s interbank direct debit mechanism, allowing billers to pull payments from customers’ bank accounts with mandate authorization (https://emis.ao/#:~:text=Image%3A%201400X1200%20Site%20Com%20Frame,SDD). It was developed to modernize recurring payments like utility bills, insurance premiums, and loan repayments. Under this system, customers sign a direct debit mandate with the service provider, and EMIS facilitates the automated debiting through participating banks. The direct debit system complements the credit transfer and card systems, providing convenience for regular obligations. Its adoption is gradually increasing as more billers join and customer trust builds. In a country where many bills were paid in cash or in person, direct debits are a leap in banking convenience and financial inclusion. By consolidating routine payments, it also encourages more people to maintain bank accounts. The service is expected to reach significant volume as major utilities and telecoms migrate customers to direct debit over time. | H39: https://thepaymentsatlas.com/country/AO
A40: Angola | B40: AO | D40: Multicaixa | E40: National payment network | F40: https://www.emis.africa/company/emolumento-sociedade-de-pagamentos-sa | H40: https://thepaymentsatlas.com/country/AO
A41: Angola | B41: AO | D41: MOVICEL Money | E41: Mobile wallet service | F41: https://www.movicel.co.ao/movicel-money/ | H41: https://thepaymentsatlas.com/country/AO
A42: Angola | B42: AO | D42: Unitel Money (Mobile Wallet) | E42: Telecom-led mobile money service for the unbanked | F42: https://unitel.co.ao/money | G42: Unitel Money is Angola’s largest mobile money platform, allowing users to open an e-wallet tied to their mobile number and perform basic financial transactions (cash deposits/withdrawals via agents, P2P transfers, merchant payments, etc.) on their phone without a bank account (https://www.menosfios.com/en/carteira-digital-unitel-money-movimenta-50-mil-milhoes-kz-em-2024/#:~:text=O%C2%A0UnitelMoney%2C%20mobile%20and%20instant%20payments,of%202024) (https://www.menosfios.com/en/carteira-digital-unitel-money-movimenta-50-mil-milhoes-kz-em-2024/#:~:text=The%20data%20was%20recently%20revealed,only%205%2C7%20million%20bank%20accounts). Launched by telecom operator Unitel in late 2019, it has grown to ~1.9 million active customers by 2024 (https://www.menosfios.com/en/carteira-digital-unitel-money-movimenta-50-mil-milhoes-kz-em-2024/#:~:text=The%20data%20was%20recently%20revealed,only%205%2C7%20million%20bank%20accounts). In the first 9 months of 2024, Unitel Money moved over 50 billion Kz in transactions (https://www.menosfios.com/en/carteira-digital-unitel-money-movimenta-50-mil-milhoes-kz-em-2024/#:~:text=O%C2%A0UnitelMoney%2C%20mobile%20and%20instant%20payments,of%202024). The service operates through a network of 50,000+ agent kiosks nationwide (https://www.menosfios.com/en/carteira-digital-unitel-money-movimenta-50-mil-milhoes-kz-em-2024/#:~:text=BUT%3A%20Unitel%20Money%20digital%20wallet,reaches%201%2C9%20million%20active%20customers). It targets financial inclusion in Angola’s largely cash-based, unbanked population. The central bank regulates it as a Payment Service Provider under the 2017 Mobile Payments law (https://www.menosfios.com/en/carteira-digital-unitel-money-movimenta-50-mil-milhoes-kz-em-2024/#:~:text=According%20to%20the%20Implementation%20Strategy,on%20behalf%20of%20customers). Adoption is strong especially in urban centers and marketplaces, though digital and financial literacy remain challenges (https://www.menosfios.com/en/carteira-digital-unitel-money-movimenta-50-mil-milhoes-kz-em-2024/#:~:text=In%20Angola%2C%20Unitel%20Money%27s%20customer,INACOM%29%20from%20last%20year). Unitel Money, together with bank-led mobile apps, is transforming everyday payments and remittances in Angola’s informal economy by offering a safe digital cash alternative. | H42: https://thepaymentsatlas.com/country/AO
A43: Angola | B43: AO | D43: Multicaixa Network | E43: National ATM/POS card payment network | F43: https://multicaixa.ao | G43: **Multicaixa** is Angola’s unified interbank card payment network, managed by EMIS (https://emis.ao/#:~:text=Image%3A%20Emis%20Img%20Destaque%20HPB1) (https://emis.ao/#:~:text=Gest%C3%A3o%20de%20rede%20partilhada%20de,aceita%C3%A7%C3%A3o%20de%20pagamentos%20com%20cart%C3%A3o). It links all ATMs (Caixas Automáticos) and POS terminals into one shared system so that any bank’s card can be used at any terminal nationwide. Banks issue debit cards (often co-badged Visa/Mastercard plus Multicaixa). Multicaixa handles switching, clearing and settlement of card transactions in local currency (https://emis.ao/#:~:text=Gest%C3%A3o%20de%20rede%20partilhada%20de,aceita%C3%A7%C3%A3o%20de%20pagamentos%20com%20cart%C3%A3o). It is widely adopted: as of 2023 there were 6+ million cards and 3,000+ ATMs in Angola, and the Multicaixa system processed **283 million** card transactions in a recent year (https://emis.ao/#:~:text=Estat%C3%ADsticas) (https://emis.ao/#:~:text=%2B) (mostly ATM withdrawals, balance inquiries, and a growing number of POS payments). Multicaixa follows international standards (EMV) and has greatly improved convenience, eliminating isolated bank-specific ATM networks. The network is connected to online payment gateways and mobile channels (e.g. Multicaixa Express app) (https://emis.ao/#:~:text=A%20EMIS%20%C3%A9%20respons%C3%A1vel%20pela,base%20nas%20melhores%20pr%C3%A1ticas%20internacionais). With very high usage, Multicaixa is the backbone of retail electronic payments in Angola, replacing cash for many day-to-day transactions. | H43: https://thepaymentsatlas.com/country/AO
A44: Angola | B44: AO | D44: Multicaixa Express | E44: Mobile banking and wallet app linked to Multicaixa | F44: https://multicaixa.ao/express | G44: Multicaixa Express (MCX Express) is a mobile application that lets customers aggregate multiple Multicaixa bank cards in one app for convenient payments (https://emis.ao/#:~:text=AS%20NOSSAS%20MARCAS%20MULTICAIXA%20A,Saiba%20Mais). It enables features like P2P transfers by phone number, bill payments, mobile airtime purchases, and QR code payments, all debiting the user’s linked bank accounts/cards. Launched by EMIS to promote digital payments, MCX Express provides an interbank mobile wallet experience. As of 2022, MCX Express had hundreds of thousands of users. It supports tokenized card details for security and uses one-time PINs for authentication. By associating cards from different banks, customers can effectively have a unified mobile banking interface (https://emis.ao/#:~:text=AS%20NOSSAS%20MARCAS%20MULTICAIXA%20A,Saiba%20Mais). This service drives financial inclusion and cashless transactions, complementing the physical Multicaixa network. MCX Express adoption is growing as smartphone penetration rises and more merchants accept its QR code or reference number payments. It forms a pillar of Angola’s digital payment innovation alongside the new instant payment system (KWiK). | H44: https://thepaymentsatlas.com/country/AO
A45: Angola | B45: AO | D45: KWiK Instant Payment System | E45: 24/7 instant account-to-account transfers (Angola) | F45: https://kwik.ao | G45: KWiK is Angola’s instant payments platform introduced by EMIS in 2022 (https://emis.ao/#:~:text=KWiK%2C%20o%20kwanza%20instant%C3%A2neo) (https://emis.ao/#:~:text=KWiK%2C%20o%20kwanza%20instant%C3%A2neo). It enables real-time, interoperable transfers between bank accounts via mobile or online channels, available 24/7. KWiK transactions complete within seconds and use the recipient’s phone number or other proxy for routing. The system is supported by the **STI (Sistema de Transferências Instantâneas)** infrastructure (https://emis.ao/#:~:text=KWiK%2C%20o%20kwanza%20instant%C3%A2neo). By 2023, KWiK processed around **2.9 million** instant transactions (https://emis.ao/#:~:text=KWiK), reflecting rapid uptake. Customers can send money instantly for P2P payments, merchant payments (via QR code or reference), and more, without waiting for batch clearing. All major banks are connected, and telco-led wallets can also interoperate via KWiK. Adoption is growing strongly as the public sees the benefit of immediate fund availability. KWiK is a key part of BNA’s strategy to modernize retail payments, offering an Angolan equivalent to “faster payment” systems seen globally. It is symbolized by the Kwanza currency’s name (KWiK) and is expected to reduce dependence on cash when fully scaled. | H45: https://thepaymentsatlas.com/country/AO
A46: Angola | B46: AO | D46: Multicaixa Network & KWiK | E46: Switch run by EMIS; supports 3 868 ATMs, POS, MCX Express app and KWiK instant wallet linked to cards/accounts. | F46: https://emis.ao | H46: https://thepaymentsatlas.com/country/AO
A47: Angola | B47: AO | D47: SPTR (Sistema de Pagamentos em Tempo Real) | E47: Operated by Banco Nacional de Angola; first phase 2022, expanded Jan 2024 to weekend availability. | F47: https://www.bna.ao | H47: https://thepaymentsatlas.com/country/AO
A48: Angola | B48: AO | D48: CCAA – Câmara de Compensação Automatizada de Angola | E48: Operated by EMIS; clears credit transfers (STC), cheques (SCC), direct debits and instant transfers (STI). Multilateral net positions settled in SPTR. | F48: https://emis.ao | H48: https://thepaymentsatlas.com/country/AO
A49: Angola | B49: AO | D49: SPTR (Sistema de Pagamento em Tempo Real) | E49: Angola’s real-time gross settlement system | F49: https://www.bna.ao | G49: SPTR is the RTGS system operated by Banco Nacional de Angola for real-time settlement of high-value payments in Angolan kwanza. All commercial banks and the central bank participate. SPTR settles interbank transfers, treasury payments, and other large transactions individually with immediate finality. It has been in use since the mid-2000s, continuously modernized (https://www.angola24horas.com/economia/item/14594-bna-finaliza-testes-para-adesao-ao-sistema-de-pagamento-eletronico-da-sadc#:~:text=BNA%20finaliza%20testes%20para%20ades%C3%A3o,Integrado%20de%20Liquida%C3%A7%C3%A3o%20Eletr%C3%B3nica) (https://angolex.com/paginas/avisos/participacao-no-sistema-de-liquidacao-bruto-em-tempo-real-da-sadc-03a-2025a.html#:~:text=Aviso%20n,SPTR). SPTR is a prerequisite for banks joining international or regional settlement systems (e.g. SADC-RTGS regional platform) (https://pti.ao/bna-esclarece-ambito-da-integracao-do-kwanza-no-sistema-da-sadc/#:~:text=BNA%20esclarece%20%C3%A2mbito%20da%20integra%C3%A7%C3%A3o,pagamento%20angolanos%20ao%20sistema) (https://angolex.com/paginas/avisos/participacao-no-sistema-de-liquidacao-bruto-em-tempo-real-da-sadc-03a-2025a.html#:~:text=Aviso%20n,SPTR). Adoption is universal among banks – SPTR handles virtually all wholesale payments in Angola. The system processes thousands of transactions daily, with annual values in the tens of trillions of AOA. SPTR’s reliable operation underpins financial stability and has enabled faster monetary transfers (replacing slower manual processes). It is complemented by retail systems like EMIS for smaller payments, but for any urgent or large fund transfer in Angola, SPTR is the backbone. | H49: https://thepaymentsatlas.com/country/AO
A50: Angola | B50: AO | D50: KWiK (Kwanza Instantâneo) | H50: https://thepaymentsatlas.com/country/AO
A51: Angola | B51: AO | D51: Multicaixa (Card & ATM Network) | H51: https://thepaymentsatlas.com/country/AO
A52: Antigua and Barbuda | B52: AG | D52: ECCB DCash | F52: https://www.dcashec.com | H52: https://thepaymentsatlas.com/country/AG
A53: Antigua and Barbuda | B53: AG | D53: ABIB Mobile | F53: https://www.abibag.com | H53: https://thepaymentsatlas.com/country/AG
A54: Antigua and Barbuda | B54: AG | D54: ECCB RTGS (ECAPS) | E54: Operated by Eastern Caribbean Central Bank; settles ECD interbank and government payments in Basseterre. | F54: https://eccb-centralbank.org | H54: https://thepaymentsatlas.com/country/AG
A55: Antigua and Barbuda | B55: AG | D55: ECACH – Eastern Caribbean Automated Clearing House | E55: Uses MICR cheque imaging and NACHA-style ACH files; net positions settled in RTGS. Antigua joined 2014 rollout. | F55: https://ecach.org | H55: https://thepaymentsatlas.com/country/AG
A56: Antigua and Barbuda | B56: AG | D56: DCash (ECCB CBDC) | H56: https://thepaymentsatlas.com/country/AG
A57: Argentina | B57: AR | D57: DEBIN (Instant Debit) | E57: Real-time pull payment instrument via banking apps | F57: https://www.bcra.gob.ar/Noticias/DEBIN-nuevo-medio-de-pago-inmediato.asp | G57: DEBIN (Débito Inmediato) is an instant debit payment introduced in 2017 in Argentina. It allows a payee to request a payment from a payer’s bank account, which the payer authorizes in real-time. Essentially, it’s a pull transaction (similar to a direct debit) but executed instantly and typically initiated through online or mobile banking. DEBIN is useful for e-commerce, splitting bills, or whenever the receiver wants to prompt the payer. Once the payer approves, funds are immediately transferred. Adoption initially was slow, but has grown as more banks integrated DEBIN into their apps and as electronic wallets (like **MODO**) leverage it for interoperability. By 2022, millions of DEBIN transactions were being done annually. It complements instant credit transfers (like “transferencias inmediatas” via CBU or alias). The convenience of a payment request rather than sharing bank details has made DEBIN popular for person-to-person payments and merchant collections, driving up usage in Argentina’s evolving immediate payments landscape. | H57: https://thepaymentsatlas.com/country/AR
A58: Argentina | B58: AR | D58: MODO | E58: Unified mobile wallet by banks (P2P & QR payments) | F58: https://modo.com.ar | G58: MODO is a digital wallet platform launched in 2020 by a consortium of over 30 Argentine banks. It is a mobile app that links directly to users’ bank accounts and cards, enabling person-to-person transfers by phone contact and QR code payments to merchants. MODO provides a unified user experience across banks – any customer of a member bank can use MODO to send money instantly (the app uses immediate bank transfers under the hood). Within a year of launch, MODO reached 4+ million downloads as banks heavily promoted it. The adoption is growing, though competition exists from independent fintech wallets. MODO transactions settle via the banking rails (often using DEBIN or immediate transfers). It effectively serves as an interoperable layer for banks to compete with fintechs like MercadoPago. The wallet saw high usage particularly for P2P: by 2022, hundreds of thousands of transfers weekly. With full integration into Transferencias 3.0 QR network, MODO allows banked users to pay any QR-accepting merchant as well. It’s a key piece in Argentina’s push toward cashless payments, leveraging the trust and reach of traditional banks in a modern smartphone app. | H58: https://thepaymentsatlas.com/country/AR
A59: Argentina | B59: AR | D59: Cámara Electrónica de Compensación de Cheques (E-cheq) | E59: Electronic check clearing system | F59: https://www.coelsa.com.ar/echeq | G59: Argentina implemented the E-cheq system in 2018, converting paper cheques into electronic form. The Electronic Check Clearing House allows checks to be issued and deposited digitally, eliminating physical transport. Banks exchange e-cheques through the central system (managed by Coelsa and Nación Servicios). This system processes large volumes: in 2022 over 20 million e-cheqs were cleared, representing the majority of check volume. Settlement is faster (24 hours) and fraud is reduced via digital signatures. It played a crucial role during the pandemic when physical clearing was impractical. Adoption by businesses has been strong, though some individuals still use traditional cheques. E-cheq is integrated with the central bank’s systems, and dishonored checks are recorded electronically. The system symbolizes Argentina’s efforts to modernize traditional payment instruments. While cheque usage overall is slowly declining in favor of instant payments, e-cheq ensures the residual check payments are processed efficiently and safely. | H59: https://thepaymentsatlas.com/country/AR
A60: Argentina | B60: AR | D60: Coelsa (Automated Clearing House) | E60: Main low-value clearing house for ACH transfers | F60: https://www.coelsa.com.ar | G60: Coelsa is Argentina’s primary automated clearing house for retail payments in pesos. Banks submit bulk electronic credit transfers (payroll, suppliers, person-to-person) and direct debits to Coelsa, which nets the positions and sends results to BCRA for settlement. Coelsa operates multiple clearing cycles per business day. It also clears the “electronic check” (ECHEQ) and certain ATM network settlements. In 2021, Coelsa handled over 300 million transactions totaling ARS 15 trillion. Adoption is high – virtually all interbank ACH payments flow through Coelsa. The system has enabled nation-wide next-day fund transfers at low cost (via the service called “CBU transfers”). Coelsa works alongside smaller ACH “**Interbanking**” focusing on corporate payments, but Coelsa has the largest share. As Argentina pushes digital payments (to combat inflation’s cash handling issues), Coelsa’s volume grows steadily. It is a behind-the-scenes engine for millions of salary deposits, bill payments, and money transfers among Argentines daily. | H60: https://thepaymentsatlas.com/country/AR
A61: Argentina | B61: AR | D61: Transferencias 3.0 (Interoperable QR payments) | E61: Instant QR code payments across banks and wallets | F61: https://www.bcra.gob.ar/Noticias/Transferencias-3.0-nuevo-esquema.asp | G61: Transferencias 3.0 is an Argentine scheme (rolled out in 2020) that enables any mobile wallet or banking app to scan a standardized QR code and pay instantly to any merchant, regardless of provider. Spearheaded by BCRA, it created an open, interoperable QR network. A customer can use their preferred app (bank or fintech) to pay a merchant’s QR; the payment is routed via immediate transfer (through Coelsa or Prisma) to the merchant’s account. Funds are received in **seconds**, and fees are very low. This effectively links banks and fintechs under a common QR standard. Adoption has been **rapid** – by late 2022, over 1 million QR payments per day were occurring as big retailers and small shops alike embraced QR acceptance. It leverages the alias/CBU instant payment infrastructure for settlement. Transferencias 3.0 significantly expanded digital payments acceptance in Argentina’s cash-heavy economy, as even micro-merchants only need a printed QR. The central bank touts it as a model for interoperability and financial inclusion. It is still growing and evolving (e.g. supporting credit in the future). | H61: https://thepaymentsatlas.com/country/AR
A62: Argentina | B62: AR | D62: ATM Networks (Red Link & Banelco) | E62: Interbank ATM and debit networks | F62: https://www.redlink.com.ar / https://www.prismamediosdepago.com | G62: Argentina has two major ATM/POS networks: **Red Link** (owned by public banks) and **Banelco** (private banks). They act as switches connecting ATMs and enabling debit card transactions. Together, they ensure nationwide interoperability: a card from a Link bank can use a Banelco ATM, and vice versa, through reciprocal agreements or the central switch. These networks also power home banking and bill pay services. In 2021, there were ~18,000 ATMs countrywide, and card withdrawals & purchases through these networks exceeded 1 billion transactions. **Prisma Medios de Pago** (which runs Banelco and processes Visa) and Red Link process the majority of card payments. Adoption is very high – nearly all banked Argentines have a debit card on one of these networks. Red Link had ~14 million cards, Banelco ~12 million (some overlap via dual-network cards). They have also introduced innovations like biometrics at ATMs and mobile ATM withdrawals. While the networks historically competed, the advent of digital wallets and Transferencias 3.0 has led them to collaborate on interoperability. They remain critical infrastructure: in cash-reliant Argentina, ATM networks serve huge withdrawal volumes, and as cashless grows, they are adapting to handle more electronic payment routing as well. | H62: https://thepaymentsatlas.com/country/AR
A63: Argentina | B63: AR | D63: Argentina RTGS (MEP) | E63: High-value Real-Time Gross Settlement (MEP/Siopel) | F63: http://www.bcra.gob.ar | G63: Argentina’s central bank (BCRA) operates an RTGS system often referred to as **MEP (Módulo Electrónico de Pagos)**. It settles large-value interbank transfers in Argentine pesos on a real-time, gross basis, providing immediate finality. MEP is used for interbank money market operations, government securities settlement, and other urgent payments. In 2022, the RTGS processed an average of ~17,000 transactions per day with daily value around ARS 1.5 trillion (figures illustrative). All banks maintain accounts at BCRA for RTGS settlement. Adoption is very high among financial institutions – RTGS is mandatory for systemic risk mitigation. The system typically operates during business hours with multiple clearing sessions for lower-value netting as well. The RTGS’s robust usage is evidenced by value throughput exceeding several times GDP annually. BCRA continuously upgrades the platform (integrating ISO 20022 messaging, etc.). MEP ensures Argentina’s financial system can transfer high-value funds securely even amid economic volatility. | H63: https://thepaymentsatlas.com/country/AR
A64: Argentina | B64: AR | D64: Transferencias 3.0 | E64: Launched Nov 2020 by BCRA with Coelsa, Fiserv, Prisma & Red Link; 24/7 push transfers settled in MEP within 25 s; max merchant fee 0.8%. | F64: https://www.bcra.gob.ar/ | H64: https://thepaymentsatlas.com/country/AR
A65: Argentina | B65: AR | D65: Electronic Means of Payment (MEP) | E65: Core interbank settlement system | F65: https://www.bcra.gob.ar/ | H65: https://thepaymentsatlas.com/country/AR
A66: Argentina | B66: AR | D66: Boleto/Offline Cash | E66: Cash-based payment vouchers | F66: https://www.bcra.gob.ar/ | H66: https://thepaymentsatlas.com/country/AR
A67: Argentina | B67: AR | D67: Cabal/Tarjeta Naranja | E67: Domestic card schemes | F67: https://www.tarjetanaranja.com.ar/ | H67: https://thepaymentsatlas.com/country/AR
A68: Argentina | B68: AR | D68: MEP (RTGS) | E68: BCRA-operated RTGS settling ARS payments and COELSA net positions in real time. | F68: https://www.bcra.gob.ar | H68: https://thepaymentsatlas.com/country/AR
A69: Argentina | B69: AR | D69: COELSA – Cámara Electrónica de Compensación | E69: Private clearing house authorised by BCRA; settles via MEP daily; NACHA-based file formats. | F69: https://www.coelsa.com.ar | H69: https://thepaymentsatlas.com/country/AR
A70: Argentina | B70: AR | D70: MEP (Electronic Means of Payment - RTGS) | H70: https://thepaymentsatlas.com/country/AR
A71: Armenia | B71: AM | D71: ArCa (Armenian Card) National System | E71: Domestic card payment network and processor | F71: https://arca.am | G71: ArCa is Armenia’s national payment card scheme and processing center, launched in 2000 by CBA and local banks (https://old.arca.am/en/about-us#:~:text=ArCa%20is%20processing%20center%20and,of%20ArCa%20National%20Payment%20System). ArCa issues domestic cards (denominated in AMD) and also processes international cards (Visa, MasterCard, Amex, etc.) for Armenian banks (https://old.arca.am/en/about-us#:~:text=payment%20and%20development%20technologies%20can,system%20cards) (https://old.arca.am/en/about-us#:~:text=commercial%20banks%20to%20produce%20and,system%20cards). The ArCa network interconnects ATMs and POS terminals countrywide, ensuring any ArCa card works across all banks. Products include ArCa Classic (debit), ArCa Credit, ArCa Gift, etc (https://arka.am/en/news/economy/7371/#:~:text=In%20particular%2C%208133%20plastic%20cards,10314%29%20and) (https://old.arca.am/en/about-us#:~:text=About%20us%20,Bank%20of%20Republic%20of%20Armenia). By 2024, ArCa had ~900k active cards in circulation (19 banks participate) (https://arka.am/en/news/business/armenian_card_payment_system_issues_29_200_new_plastic_cards_in_july/?sphrase_id=2231479#:~:text=More%20specifically%2C%20it%20issued%2010%2C077,make%20transactions%20in%20July%20exceeded) (https://arka.am/en/news/business/armenian_card_payment_system_issues_29_200_new_plastic_cards_in_july/?sphrase_id=2231479#:~:text=Some%20624%2C591%20cards%20were%20used,3). In 2021, about 330k ArCa cardholders were active, making ~33% more transactions vs prior year (https://arka.am/en/news/business/armenian_card_payment_system_issues_29_200_new_plastic_cards_in_july/?sphrase_id=2231479#:~:text=Some%20624%2C591%20cards%20were%20used,3) (https://arka.am/en/news/business/armenian_card_payment_system_issues_29_200_new_plastic_cards_in_july/?sphrase_id=2231479#:~:text=Some%20624%2C591%20cards%20were%20used,3). ArCa also provides a 24/7 processing center and fraud monitoring (https://old.arca.am/en/about-us#:~:text=What%20we%20do). Many ArCa cards are co-badged with MasterCard or Visa for international acceptance. The system has high adoption domestically – ArCa cards are widely used for cash withdrawals and AMD-denominated purchases. It’s a crucial infrastructure for cashless payments in Armenia, handling millions of ATM/POS transactions monthly and unifying the country’s card payments under local governance. | H71: https://thepaymentsatlas.com/country/AM
A72: Armenia | B72: AM | D72: IDram & TelCell Wallets | E72: Leading electronic money and QR payment platforms | F72: https://idram.am / https://telcell.am | G72: Idram and TelCell are popular non-bank e-wallets in Armenia enabling digital payments and money transfers. **Idram**, launched 2008, has ~1.5 million registered users and processed 55 million transactions in 2022 (https://armenian-lawyer.com/business-immigration/payment-processing-armenia/#:~:text=Guide%20to%20Payment%20Processing%20Solutions,store%20%28via%20QR). It offers a mobile app for P2P transfers, bill payments, online purchases, and an extensive QR code payment network. Over 22,000 retail locations accept Idram QR, and ~200k users made 4 million QR payments in the first 9 months of 2024 (https://armenpress.am/en/article/1199415#:~:text=with%20flexible%20payment%20terms%20ranging,from%201%20to%2012%20months) (https://armenpress.am/en/article/1199415#:~:text=In%20terms%20of%20statistics%2C%20over,modern%20tools%20like%20Rocket%20Line). **TelCell** similarly provides e-wallet services and a nationwide kiosk network for top-ups. These fintech platforms are integrated with banks (Idram partnered with IDBank) and have introduced innovations like “Buy Now Pay Later” (Rocket Line). Adoption is growing rapidly as they cater to a tech-savvy population and provide alternatives to cash. They are licensed by CBA as payment organizations. Their transaction volumes – tens of millions annually – reflect Armenians’ embrace of mobile payments for everything from utilities to groceries. They also promote interoperability; e.g., Idram is working on allowing other banks’ apps to scan Idram QR codes (https://armenpress.am/en/article/1199415#:~:text=In%20summary%2C%20%E2%80%9CIdram%20for%20Everyone%E2%80%9D,a%20wide%20range%20of%20platforms) (https://armenpress.am/en/article/1199415#:~:text=,and%20your%20partner%20financial%20institutions). These wallets significantly contribute to Armenia’s digital payment ecosystem growth. | H72: https://thepaymentsatlas.com/country/AM
A73: Armenia | B73: AM | D73: TelCell | E73: Mobile wallet | F73: https://telcell.am | H73: https://thepaymentsatlas.com/country/AM
A74: Armenia | B74: AM | D74: ArCa | E74: National card system | F74: https://arca.am | H74: https://thepaymentsatlas.com/country/AM
A75: Armenia | B75: AM | D75: Electronic Payment System (EPS) | E75: Central Bank of Armenia’s RTGS system | F75: https://www.cba.am/en/SitePages/epayments.aspx | G75: EPS is Armenia’s real-time gross settlement system operated by the Central Bank of Armenia (CBA) (https://www.cba.am/en/what-payment-and-settlement-systems-do-we-operate#:~:text=Electronic%20Payment%20System%20of%20the,Central%20Bank%20of%20Armenia) (https://www.cba.am/en/what-payment-and-settlement-systems-do-we-operate#:~:text=and%20ensuring%20the%20optimal%20functionality,financial%20needs%20within%20the%20Armenian). Established in 1997, it is the backbone of interbank payments, settling high-value and time-critical fund transfers in dram. The CBA acts as operator, settlement agent, and overseer (https://www.cba.am/en/what-payment-and-settlement-systems-do-we-operate#:~:text=The%20electronic%20payment%20system%20stands,transaction%20basis.%20Remarkably) (https://www.cba.am/en/what-payment-and-settlement-systems-do-we-operate#:~:text=this%20system%20exclusively%20handles%20credit,needs%20within%20the%20Armenian%20economy). EPS runs in real-time during banking hours, processing credit transfers between banks with immediate finality (no amount limits) (https://www.cba.am/en/what-payment-and-settlement-systems-do-we-operate#:~:text=and%20ensuring%20the%20optimal%20functionality,financial%20needs%20within%20the%20Armenian). Both wholesale (large-value, interbank) and retail payments can be settled, though typically large-value and urgent transactions use EPS. Participants include all commercial banks, the Ministry of Finance, the ArCa card system operator, and others (https://www.cba.am/en/what-payment-and-settlement-systems-do-we-operate#:~:text=The%20main%20participants%20of%20the,Ministry%20of%20Finance%2C%20international%20banks). By providing irrevocable settlement, EPS ensures safety in the financial system. In recent years it processed around 2–3 million transactions annually (with value in the trillions of AMD). Adoption is universal among financial institutions. EPS’s continuous enhancements (e.g., extended operating hours) support Armenia’s growing payment volumes and integration with international systems. | H75: https://thepaymentsatlas.com/country/AM
A76: Armenia | B76: AM | D76: ArCa National Payment System | E76: Armenian Card CJSC processes ArCa, Visa, MasterCard, MIR, etc.; provides ATM/POS, clearing and settlement; 280+ members. | F76: https://arca.am | H76: https://thepaymentsatlas.com/country/AM
A77: Armenia | B77: AM | D77: Central Bank Electronic Payment System (CBANet RTGS) | E77: Operated by Central Bank of Armenia; 24/7 since 2021; also settles securities and net ACH. | F77: https://www.cba.am | H77: https://thepaymentsatlas.com/country/AM
A78: Armenia | B78: AM | D78: ArCa Pay Instant Transfer | E78: Launched Nov 2024; Ameriabank, Evocabank and Converse Bank live; STP < 10 s. | F78: https://arca.am/arcapay | H78: https://thepaymentsatlas.com/country/AM
A79: Armenia | B79: AM | D79: FAST System (Instant Payments) | E79: Upcoming instant account transfer initiative | F79: https://www.cba.am | G79: Armenia is developing a national instant payment system (often referred to as a FAST system) to enable 24/7 immediate transfers between banks. While as of 2024 Armenia doesn’t yet have a fully launched instant payment rail, CBA has signaled interest in modernizing to support near-real-time retail payments (inspired by systems like PIX, UPI) (https://armenpress.am/en/article/1199415#:~:text=Yes%2C%20you%E2%80%99re%20correct,market%20participants%20have%20joined%20it). Some elements exist: for example, ArCa and Idram facilitate quasi-instant P2P transfers. However, a centralized instant payment scheme with proxy addressing (phone/email) and broad adoption is in planning. Pilot projects with a few banks may start by 2025. This would allow a person to send drams to another within seconds at any time, which today is possible only within the same bank or via certain wallet networks. The system would likely integrate QR codes and tie into ArCa’s infrastructure for interoperability. In short, while not operational yet, Armenia’s “FAST” payment initiative is in a research/pilot stage and expected to elevate the country’s payment capabilities to real-time in the near future. | H79: https://thepaymentsatlas.com/country/AM
A80: Armenia | B80: AM | D80: MobiDram | E80: Cross-platform mobile payment system operated by Viva for mobile operator payments and card top-ups. | G80: MobiDram is a mobile payment platform operated by Viva (one of Armenia's three major mobile operators) that enables payments for mobile services across all three operators (Viva, Team Telecom, and Ucom) and top-ups for bank cards. Following the termination of cooperation with independent payment systems in February 2026, MobiDram has become a primary channel for mobile balance recharging. | H80: https://thepaymentsatlas.com/country/AM
A81: Armenia | B81: AM | D81: TeamPay | E81: Commission-free mobile payment platform operated by Team Telecom for payments across all three mobile operators. | H81: https://thepaymentsatlas.com/country/AM
A82: Armenia | B82: AM | D82: Upay / U! Pay | E82: Mobile payment platform operated by Ucom for payments across all three mobile operators. | H82: https://thepaymentsatlas.com/country/AM
A83: Australia | B83: AU | D83: New Payments Platform (NPP) | E83: Real-time retail payment system | F83: https://www.nppa.com.au/ | H83: https://thepaymentsatlas.com/country/AU
A84: Australia | B84: AU | D84: Direct Entry System | E84: Bulk electronic clearing | F84: https://www.apca.com.au/ | H84: https://thepaymentsatlas.com/country/AU
A85: Australia | B85: AU | D85: RITS (RTGS) | E85: Real-time gross settlement | F85: https://www.rba.gov.au/payments-and-infrastructure/rits/ | H85: https://thepaymentsatlas.com/country/AU
A86: Australia | B86: AU | D86: Card Schemes | E86: Regulated debit/credit networks | F86: https://www.visa.com.au/ and https://www.mastercard.com.au/ | H86: https://thepaymentsatlas.com/country/AU
A87: Australia | B87: AU | D87: Buy Now Pay Later (BNPL) | E87: Unregulated installment credit | F87: https://www.afterpay.com/ | H87: https://thepaymentsatlas.com/country/AU
A88: Australia | B88: AU | D88: RITS (Reserve Bank Information and Transfer System) | E88: RITS is the RTGS system operated by the Reserve Bank of Australia for settling large-value interbank payments in real time. It handles transactions in Australian dollars including interbank transfers, money market settlements, and time-critical customer payments. RITS has very high usage – in 2021/22 it processed on average **2.2 million transactions per day** (thanks to integration with retail batch traffic), worth over AUD 200 billion daily. All banks and many other financial institutions hold RITS accounts. RITS also settles net obligations from other systems (cheque clearing, card networks, etc.). Transactions in RITS are final and irrevocable, greatly reducing settlement risk. The system operates on an RTGS platform (new RITS launched 1998) with SWIFT messaging; it has extended hours to support foreign exchange PvP settlement. RITS’s reliability and throughput make it one of the world’s most robust RTGS systems. It is critical infrastructure – if RITS stops, so do most payments in Australia. Adoption is universal among banks (100+ participants) and it underpins all other payment schemes by providing ultimate settlement in central bank money. | F88: https://www.rba.gov.au/payments-and-infrastructure/rits/ | G88: RITS is the RTGS system operated by the Reserve Bank of Australia for settling large-value interbank payments in real time. It handles transactions in Australian dollars including interbank transfers, money market settlements, and time-critical customer payments. RITS has very high usage – in 2021/22 it processed on average **2.2 million transactions per day** (https://www.rba.gov.au/publications/annual-reports/rba/2022/banking-and-payment-services.html#:~:text=Reserve%20Bank%20of%20Australia%20Annual,2%20million) (https://www.rba.gov.au/publications/annual-reports/rba/2022/banking-and-payment-services.html#:~:text=Compared%20with%20the%20previous%20financial,2%20million) (thanks to integration with retail batch traffic), worth over AUD 200 billion daily. All banks and many other financial institutions hold RITS accounts. RITS also settles net obligations from other systems (cheque clearing, card networks, etc.). Transactions in RITS are final and irrevocable, greatly reducing settlement risk. The system operates on an RTGS platform (new RITS launched 1998) with SWIFT messaging; it has extended hours to support foreign exchange PvP settlement. RITS’s reliability and throughput make it one of the world’s most robust RTGS systems. It is critical infrastructure – if RITS stops, so do most payments in Australia. Adoption is universal among banks (100+ participants) and it underpins all other payment schemes by providing ultimate settlement in central bank money. | H88: https://thepaymentsatlas.com/country/AU
A89: Australia | B89: AU | D89: New Payments Platform (NPP) – Osko/PayID | E89: Instant 24/7 bank transfers and addressing service | F89: https://www.nppa.com.au | G89: The NPP is Australia’s instant payments system launched in 2018, enabling near-real-time fund transfers between banks 24/7. It features the overlay service **Osko** (by BPAY) for fast P2P payments and a proxy addressing system **PayID** (which lets users link mobile/email to their account). NPP has been widely adopted: as of 2022, about **100 million** transactions per month were being processed (https://www.auspayplus.com.au/npp-roadmap-provides-update-on-the-platforms-uptake-and-capability-development#:~:text=NPP%20Roadmap%20provides%20update%20on,more%20than%20100%20million), with ~89 million bank accounts reachable via NPP (https://www.auspayplus.com.au/npp-roadmap-provides-update-on-the-platforms-uptake-and-capability-development#:~:text=NPP%20Roadmap%20provides%20update%20on,more%20than%20100%20million). On an average day, NPP handles 2.8 million transactions worth ~A$3 billion (https://www.hellozai.com/blog/australia-payment-statistics#:~:text=Australia%20payment%20statistics%3A%20A%20roundup,average%20value%20of%20NPP) (https://www.hellozai.com/blog/australia-payment-statistics#:~:text=registered%20PayIDs,average%20value%20of%20NPP). Consumers have embraced services like Osko for splitting bills and instant transfers – 75+ banks and fintechs participate. Businesses and government also use NPP for immediate payments (e.g., emergency welfare disbursements). The NPP supports richer data and real-time confirmation. In 2022, it added **PayTo**, a new capability for merchant-initiated debits replacing direct debits. Overall, NPP’s adoption is high and growing (transaction volumes rose ~40% YoY) (https://www.rba.gov.au/publications/annual-reports/rba/2022/banking-and-payment-services.html#:~:text=Reserve%20Bank%20of%20Australia%20Annual,2%20million) (https://www.rba.gov.au/publications/annual-reports/rba/2022/banking-and-payment-services.html#:~:text=Compared%20with%20the%20previous%20financial,2%20million). It has become a core national infrastructure for everyday payments, complementing older systems (which it will progressively supersede). NPP is managed by Australian Payments Plus (AP+). | H89: https://thepaymentsatlas.com/country/AU
A90: Australia | B90: AU | D90: BPAY | E90: Electronic bill payment system via banking channels | F90: https://www.bpay.com.au | G90: BPAY is Australia’s most widely used bill payment service which enables bill payers to transfer funds electronically from their bank accounts to billers (https://www.westpac.com.au/business-banking/merchants-and-payments/manage/merchant-guides/bpay-faqs/#:~:text=1) (https://www.westpac.com.au/business-banking/merchants-and-payments/manage/merchant-guides/bpay-faqs/#:~:text=Since%20BPAY%C2%A0%E2%80%99s%20launch%20in%201997%2C,over%2018%20million%20individual%20payments). It is offered as a payment channel by over 170 financial institutions through their phone and Internet banking services. Since BPAY’s launch in 1997, electronic bill payment in Australia has grown at a phenomenal rate. BPAY can be used to pay over 16,000 different bills Australia wide and each month BPAY processes over 18 million individual payments (https://www.westpac.com.au/business-banking/merchants-and-payments/manage/merchant-guides/bpay-faqs/#:~:text=Since%20BPAY%C2%A0%E2%80%99s%20launch%20in%201997%2C,over%2018%20million%20individual%20payments). Over the last couple of years there has been a substantial increase in the number of people who have access to internet banking which has resulted in a large increase in the number of people using BPAY. Now 76% of the Australian bill paying population use BPAY (https://www.westpac.com.au/business-banking/merchants-and-payments/manage/merchant-guides/bpay-faqs/#:~:text=Over%20the%20last%20couple%20of,being%20made%20via%20the%20internet) with 85% of BPAY payments being made via the internet. BPAY offers an efficient and user-friendly solution for receiving payments that provides significant cost and time benefits for not only you, but your customers too. | H90: https://thepaymentsatlas.com/country/AU
A91: Australia | B91: AU | D91: eftpos | E91: Domestic debit card network and scheme | F91: https://www.auspayplus.com.au/eftpos | G91: eftpos (electronic funds transfer at point of sale) is Australia’s homegrown debit card network, established in the 1980s. It connects all banks’ ATM and POS systems, allowing immediate deduction from bank accounts for purchases and cash-outs. eftpos is ubiquitous – virtually every Australian debit card (and many Medicare/social benefit cards) had eftpos functionality, often co-badged with Visa/Mastercard. In 2019/20, Australian cardholders made around 10.7 billion debit and credit card purchases worth $677 billion, with cards accounting for three-quarters of these payments (https://www.rba.gov.au/publications/annual-reports/psb/2020/trends-in-payments-clearing-and-settlement-systems.html#:~:text=Trends%20in%20Payments%2C%20Clearing%20and,quarters%20of%20the). A large share of these are eftpos PIN debit transactions at merchants. Adoption is universal among merchants – over 900,000 payment terminals accept eftpos. In FY2022, around 2.6 billion eftpos transactions were made (rough estimate). The scheme has innovated with contactless (eftpos Tap & Pay), mobile wallet integration, and an online payment capability to compete with global networks. eftpos is now part of Australian Payments Plus and is working on new services like digital identity and real-time deposit via NPP. It remains critical for low-cost domestic card payments (notably, it offers least-cost routing which retailers favor to reduce fees). Though credit cards have rewards, eftpos debit is still heavily used for everyday purchases and cash withdrawals at retail (cash-out service). | H91: https://thepaymentsatlas.com/country/AU
A92: Australia | B92: AU | D92: Direct Entry (BECS) | E92: Legacy ACH system for batched payments | F92: https://www.auspaynet.com.au/systems/becs | G92: The Bulk Electronic Clearing System (BECS), commonly called Direct Entry, is Australia’s traditional ACH used for decades to process batched direct credits and debits (e.g., payroll, supplier payments, recurring debits). Banks exchange files of transactions which are netted and settled the next day through RBA. Direct Entry has been the workhorse for non-urgent payments: in 2022 it still processed a significant volume (e.g., over 3 billion transactions for salaries, invoices, etc.). Adoption is universal among businesses/government for regular payments – e.g., the Australian Taxation Office uses direct debits for taxes. However, its growth has plateaued as the NPP’s PayID/PayTo begin to replace it. Still, in FY2022, Direct Entry volumes grew by around 1% annually amid strong population and economic growth. It operates on a deferred net cycle, typically overnight. Direct credits reach accounts by next morning; direct debits allow some days for dishonours. The system is low-cost but lacks real-time speed. Under industry plans, newer systems (NPP’s PayTo) will gradually migrate volume off BECS by 2024-2025. Until then, BECS remains critical infrastructure – for instance, bulk government benefit payments (Centrelink) use Direct Entry. The RBA oversees BECS via AusPayNet regulations. It’s reliable but technologically dated, being one of the last batch systems in an increasingly instant world. | H92: https://thepaymentsatlas.com/country/AU
A93: Australia | B93: AU | D93: Cheque System (Paper Clearing) | E93: Paper cheque clearing system (phasing out) | F93: https://www.auspaynet.com.au/systems/APCS | G93: Australia’s cheque clearing system is a declining but still operational payment scheme. Banks clear cheques via exchanging digital cheque images and data, with net settlement through RITS. Cheque volumes have fallen dramatically – in 2022, the annual volume was under 20 million (compared to 300+ million in 1995). The system is managed under AusPayNet’s APCS (Australian Paper Clearing System). Processing time is typically 3 days (T+2). The government and banks have committed to phase out cheques by 2030 or sooner due to high costs and low usage. As of 2023, fewer than 0.2% of non-cash payments were by cheque. However, older demographics and some business use cases (like bank cheques for real estate deposits) still utilize cheques, so the system remains for now. Its adoption is **low** and falling. In the latest financial year, government cheque payment volume fell by a further 5% (https://www.rba.gov.au/publications/annual-reports/rba/2023/pdf/banking-and-payment-services.pdf#:~:text=The%20annual%20cheque%20payment%20volume,Source%3A%20RBA). Banks are closing cheque services gradually. Cheques historically played an important role, but today serve mostly as a legacy payment option. The cheque clearing system will likely be the first major payment system to be entirely retired in Australia’s modern era. | H93: https://thepaymentsatlas.com/country/AU
A94: Australia | B94: AU | D94: NPP – New Payments Platform | E94: Went live Feb 2018; >100 institutions connected; funds in < 10 s, 24×7; settled via RBA FSS. | F94: https://nppa.com.au | H94: https://thepaymentsatlas.com/country/AU
A95: Australia | B95: AU | D95: BECS (Bulk Electronic Clearing System) | E95: Managed by AusPayNet; five intraday settlements via RITS. Industry plan to decommission by 2030 as volumes migrate to NPP. | F95: https://www.auspaynet.com.au/resources/New-To-Payments-5 | H95: https://thepaymentsatlas.com/country/AU
A96: Australia | B96: AU | D96: NPP (New Payments Platform) | H96: https://thepaymentsatlas.com/country/AU
A97: Austria | B97: AT | D97: EPS | E97: Online banking payments | F97: https://www.eps-ps.at | H97: https://thepaymentsatlas.com/country/AT
A98: Austria | B98: AT | D98: Bluetooth | E98: Contactless payment | F98: https://www.banksys.be | H98: https://thepaymentsatlas.com/country/AT
A99: Austria | B99: AT | D99: TARGET2 (ARTIS/T2) | E99: Euro RTGS system for Austria (part of Eurosystem) | F99: https://www.ecb.europa.eu/paym/target/t2/html/index.en.html | G99: Austria settles large-value payments in euro via TARGET2, the pan-European RTGS system. The Oesterreichische Nationalbank’s local component (previously called **ARTIS**) connects Austrian banks to TARGET2 (https://www.bis.org/publ/cpss105_eu.pdf#:~:text=,of%20euro%20payments%20in). TARGET2 processes high-value interbank transfers, monetary policy operations, and other urgent payments in central bank money. Austrian banks have used RTGS since 2002 (when ARTIS launched, then migrated to TARGET2 in 2007). Settlement is real-time and final. Nearly all domestic large payments (and many customer euro transfers) go through this system. On an average day, TARGET2-Austria handles thousands of transactions worth tens of billions of euros. Adoption is complete among banks – it’s the only channel for euro RTGS. As part of the Eurosystem’s T2, Austrian RTGS operations run 7:00–18:00 CET, with ancillary system interfacing (like securities settlement). In March 2023, TARGET2 was replaced by the new consolidated T2 platform; Austrian participants migrated accordingly. The RTGS ensures Austria’s integration in the Eurozone financial infrastructure, providing safe, immediate settlement for big payments. Its volume tends to be a few hundred thousand transactions per year in Austria, but with extremely high total value (multiple times GDP). | H99: https://thepaymentsatlas.com/country/AT
A100: Austria | B100: AT | D100: Clearing Services (Step2/TIPS) | E100: Retail euro clearing for SEPA credit transfers and instant payments | F100: https://www.stuzza.at/en/zahlungssysteme | G100: Austria does not maintain a separate national ACH for euro; instead, its banks use pan-European retail payment systems. Most SEPA Credit Transfers and Direct Debits are cleared via EBA Clearing’s **STEP2** system or bilateral arrangements and settled in TARGET2. Additionally, Austrian banks participate in SEPA Instant – many have joined EBA’s **RT1** or the Eurosystem **TIPS** to process instant euro transfers under 10 seconds. By 2023, a majority of Austrian banks offered SCT Inst to customers. The volume of SEPA retail payments is high: Austrians made about 650 electronic payments per person in 2021/22 (https://www.rba.gov.au/publications/annual-reports/psb/2022/the-evolving-retail-payments-landscape.html#:~:text=Australia%20www,per%20cent%20of%20these) (https://www.rba.gov.au/publications/annual-reports/psb/2022/the-evolving-retail-payments-landscape.html#:~:text=In%202021%2F22%2C%20Australians%20made%20around,per%20cent%20of%20these) (mostly card and credit transfers). The clearing of those goes through these Europe-wide systems. The OeNB no longer runs a domestic ACH for euro (the old clearinghouse was phased out after SEPA). However, one local system remains for some domestic purposes: the Clearing Service Austria (CS.A) run by PSA for interbank book transfers and ATM/POS netting. Still, from a scheme perspective, SEPA mechanisms dominate. Adoption of SEPA credit/debit schemes is universal and volumes continue to grow at ~7% annually. For instant payments, adoption is moderate but quickly rising as usage of SCT Inst expands across the Eurozone (Austria included). | H100: https://thepaymentsatlas.com/country/AT
...

Sheet Países
A1: País | B1: Código | C1: Região | D1: Sistemas registados (segundo o site) | E1: Sistemas extraídos | F1: Resumo do site | G1: Página no Atlas
A2: Afghanistan | B2: AF | D2: 9 | E2: =COUNTIF(Sistemas!$B:$B,B2) | G2: https://thepaymentsatlas.com/country/AF
A3: Albania | B3: AL | D3: 7 | E3: =COUNTIF(Sistemas!$B:$B,B3) | G3: https://thepaymentsatlas.com/country/AL
A4: Algeria | B4: DZ | D4: 10 | E4: =COUNTIF(Sistemas!$B:$B,B4) | G4: https://thepaymentsatlas.com/country/DZ
A5: Andorra | B5: AD | D5: 10 | E5: =COUNTIF(Sistemas!$B:$B,B5) | G5: https://thepaymentsatlas.com/country/AD
A6: Angola | B6: AO | D6: 14 | E6: =COUNTIF(Sistemas!$B:$B,B6) | G6: https://thepaymentsatlas.com/country/AO
A7: Antigua and Barbuda | B7: AG | D7: 5 | E7: =COUNTIF(Sistemas!$B:$B,B7) | G7: https://thepaymentsatlas.com/country/AG
A8: Argentina | B8: AR | D8: 14 | E8: =COUNTIF(Sistemas!$B:$B,B8) | G8: https://thepaymentsatlas.com/country/AR
A9: Armenia | B9: AM | D9: 12 | E9: =COUNTIF(Sistemas!$B:$B,B9) | G9: https://thepaymentsatlas.com/country/AM
A10: Australia | B10: AU | D10: 14 | E10: =COUNTIF(Sistemas!$B:$B,B10) | G10: https://thepaymentsatlas.com/country/AU
A11: Austria | B11: AT | D11: 16 | E11: =COUNTIF(Sistemas!$B:$B,B11) | G11: https://thepaymentsatlas.com/country/AT
A12: Azerbaijan | B12: AZ | D12: 13 | E12: =COUNTIF(Sistemas!$B:$B,B12) | G12: https://thepaymentsatlas.com/country/AZ
A13: Bahamas | B13: BS | D13: 11 | E13: =COUNTIF(Sistemas!$B:$B,B13) | G13: https://thepaymentsatlas.com/country/BS
... A198: Zimbabwe | B198: ZW | D198: 10 | E198: =COUNTIF(Sistemas!$B:$B,B198) | G198: https://thepaymentsatlas.com/country/ZW

Sheet Notas
A1: Fonte | B1: The Payments Atlas — https://thepaymentsatlas.com
A2: Data da extração | B2: 2026-10-30
A3: Conteúdo | B3: Folha 'Sistemas' = uma linha por sistema listado em 'Payment Systems' de cada país.
A4: Conferência | B4: Na folha 'Países', compare 'registados' com 'extraídos'. Diferenças indicam itens por rever.
A5: Referências [n] | B5: As notas de rodapé do tipo [107] foram removidas das descrições.
A6: Direitos | B6: Os dados pertencem ao The Payments Atlas; confirme os termos de uso antes de redistribuir.
